expressconnect/__init__.py
expressconnect/client.py
expressconnect/custompython.py
expressconnect/events.py
expressconnect/hostserver.py
expressconnect/server.py
expressconnect-0.1.0.dist-info/METADATA
expressconnect-0.1.0.dist-info/WHEEL
expressconnect-0.1.0.dist-info/top_level.txt
expressconnect-0.1.0.dist-info/RECORD
