Metadata-Version: 2.4
Name: expressconnect
Version: 0.1.0
Summary: Async websocket framework with multi-host, multitask, and custom python execution
Author: benim
License: MIT
Requires-Python: >=3.10
Requires-Dist: websockets>=12.0
